{"FBX name":"5 poses WIN Honoka C5 cabelo Miku DOA 5.fbx","Time Stamp":"Wed Nov 15 18:31:23 2017\n","Mesh names":{"Mesh 0":"24_skirt1_0.5_1_1.carca","Mesh 1":"25_alpha11_1_1_1.carca","Mesh 2":"25_alpha12_1_1_1.carca","Mesh 3":"24_pants_0.5_1_1.carca","Mesh 4":"24_face_0.9_1_1.carca","Mesh 5":"25_alpha9_1_1_1.carca","Mesh 6":"24_stock2_0.5_1_1.carca","Mesh 7":"24_skirt2_0.5_1_1.carca","Mesh 8":"24_body_0.9_1_1.carca","Mesh 9":"25_alpha10_1_1_1.carca","Mesh 10":"24_glove1_0.5_1_1.carca","Mesh 11":"24_stockings_0.4_1_1.carca","Mesh 12":"24_shoes_0.5_1_1.carca","Mesh 13":"4_ribb_0.1_1_1.carca","Mesh 14":"24_shirt_0.4_1_1.carca","Mesh 15":"26_met_0.3_1_1.carca","Mesh 16":"24_glove2_0.5_1_1.carca","Mesh 17":"24_eyes_2_1_1.carca","Mesh 18":"24_stock1_0.5_1_1.carca"},"Texture names":{"Texture 0":"hon_cos_004_cloth02_base.tga","Texture 1":"hon_sitamatuge.tga","Texture 2":"hon_cos_001_underwear_base.tga","Texture 3":"hon_face_base.tga","Texture 4":"hon_matuge_base_PP1.tga","Texture 5":"hon_cos_001_cloth02_base.tga","Texture 6":"hon_body_base.tga","Texture 7":"hon_cos_001_cloth03_base.tga","Texture 8":"hon_cos_004_other_base.tga","Texture 9":"Hair\\hair2.png","Texture 10":"hon_cos_004_cloth01_base.tga"}}